Metadata-Version: 2.1
Name: spacyspellcheck
Version: 0.0.6
Summary: spell check using spacy vocab and in built levenshtein distance
Home-page: https://github.com/Vishnunkumar/spacyspellcheck
Author: Vishnu Nandakumar
Author-email: nkumarvishnu25@gmail.com
License: MIT license
Keywords: spacyspellcheck
Classifier: Development Status :: 3 - Alpha
Classifier: Intended Audience :: Developers
Classifier: Topic :: Software Development :: Build Tools
Classifier: License :: OSI Approved :: MIT License
Classifier: Programming Language :: Python :: 3
Classifier: Programming Language :: Python :: 3.4
Classifier: Programming Language :: Python :: 3.5
Classifier: Programming Language :: Python :: 3.6
License-File: LICENSE
